erlenberg_ext/__init__.py
erlenberg_ext/simpleCrypt.py
erlenberg_ext/cryptScriptGenerator/__init__.py
erlenberg_ext/cryptScriptGenerator/__main__.py
erlenberg_ext/cryptTextGenerator/__init__.py
erlenberg_ext/cryptTextGenerator/__main__.py
erlenberg_ext-3.1.dist-info/LICENSE
erlenberg_ext-3.1.dist-info/METADATA
erlenberg_ext-3.1.dist-info/WHEEL
erlenberg_ext-3.1.dist-info/entry_points.txt
erlenberg_ext-3.1.dist-info/top_level.txt
erlenberg_ext-3.1.dist-info/RECORD
