Metadata-Version: 2.1
Name: erlenberg-ext
Version: 3.1
Summary: Some personal librarys for python (extended)
Author: Tizian Erlenberg
Author-email: mail@erlenberg.net
Classifier: Programming Language :: Python :: 3
Classifier: License :: OSI Approved :: MIT License
Classifier: Operating System :: OS Independent
Requires-Python: >=3.7
License-File: LICENSE
Requires-Dist: cryptography
